setup.py
tests/support/__init__.py
tests/support/test_vectors.py
xstream/__init__.py
xstream/x25519hkdf.py
xstream.egg-info/PKG-INFO
xstream.egg-info/SOURCES.txt
xstream.egg-info/dependency_links.txt
xstream.egg-info/not-zip-safe
xstream.egg-info/requires.txt
xstream.egg-info/top_level.txt